{
  "title": "General Entry Level - All Industries 7.1(Americas)",
  "description": "Our General Entry Level – All Industries 7.1 solution is designed for entry-level positions across industries. This solution predicts the following types of behaviors foundational to all jobs: being on-time to work; following rules and policies; treating others respectfully; producing quality work; meeting goals; and effectively working alongside others. Solution can be used across all industries with entry-level positions. Example titles include, but are not limited to: Administrator, Clerk, Veterinary Assistant, Stocker, Dish Washer, Office Coordinator, Tour Guide, Cook, Assistant, Housekeeper, Waste Collector.",
  "jobLevels": "Entry-Level,",
  "languages": "Portuguese (Brazil), French (Canada), English (USA), Latin American Spanish,",
  "assessmentLength": "Approximate Completion Time in minutes = 19",
  "productFactSheet": []
}