{
  "title": "Retail Sales Associate Solution",
  "description": "The Retail Sales Associate solution is for entry-level retail positions in which employees proactively sell products to customers and have their pay and/or performance based on sales revenue. Sample tasks for these jobs include, but are not limited to: promoting products to customers, persuading customers to buy products, and completing a transaction with a customer. Potential job titles that use this solution are: Sales Representative, Retail Sales Associate, and Sales Clerk. There are multiple configurations and versions of this solution available.",
  "jobLevels": "Entry-Level,",
  "languages": "English (USA),",
  "assessmentLength": "Approximate Completion Time in minutes = 29",
  "productFactSheet": [
    "https://service.shl.com/docs/Fact%20Sheet%20Retail%20Sales%20Associate%20One%20Sitting%20_USE.pdf"
  ]
}