{
  "title": "Dependability and Safety Instrument (DSI)",
  "description": "The DSI is a short pre-screening tool for many key entry-level roles. It is designed to identify potential employees who will have good dependability and reliability, and who are less likely to engage in counter-productive work behaviors. Note: Turkish [end June 2012] and Romanian [end May 2013] are on limited beta relase",
  "jobLevels": "Entry-Level,",
  "languages": "Portuguese (Brazil), Chinese Traditional, Danish, Dutch, Finnish, French, German, Icelandic, Chinese Simplified, English International, Italian, Latin American Spanish, Polish, Swedish, English (USA), Norwegian, Russian,",
  "assessmentLength": "Approximate Completion Time in minutes = 10",
  "productFactSheet": [
    "https://service.shl.com/docs/DSI_Fact%20Sheet.pdf"
  ]
}