{
  "title": "SHL Verify Interactive G+",
  "description": "SHL Verify Interactive G+ (SVIG+) is a test of general cognitive ability that also generates accurate assessments of three specific abilities: Deductive Reasoning, Inductive Reasoning, and Numerical Reasoning. The candidate will see questions measuring all three abilities. Candidates will receive a score on each of the specific abilities as well as a general ability score. This test is appropriate for all job levels, however it is most relevant for positions that require cognitive ability across a range of specific skills. Completion time is 36 minutes for the test itself, plus 10 minutes for instructions and practice.",
  "jobLevels": "Graduate, Manager, Mid-Professional, Professional Individual Contributor,",
  "languages": "English (USA), Chinese Traditional, Korean, Serbian, Slovak, Spanish, English International, Danish, Swedish, Norwegian, Finnish, Latvian, Lithuanian, Estonian, Portuguese, Hungarian, Thai, Czech, Polish, Turkish, Portuguese (Brazil), Romanian, Latin American Spanish, Italian, French (Canada), Chinese Simplified, Dutch, German, French, Russian, Indonesian, Greek, Japanese,",
  "assessmentLength": "Approximate Completion Time in minutes = 36",
  "productFactSheet": [
    "https://service.shl.com/docs/Verify%20Interactive%20G%20plus%20Factsheet.pdf"
  ]
}