{
  "title": "Written English v1",
  "description": "The Written English test measures knowledge of US English grammar and English reading comprehension. It is designed for those with English as a second language and covers the following topics: Articles, Comparisons, Conjunctions, General Questions, Misused Words, Nouns, Parallel Structure, Prepositions, Pronouns, Specific Questions, and Verbs.",
  "jobLevels": "Entry-Level, Front Line Manager, Mid-Professional, Professional Individual Contributor,",
  "languages": "English (USA), English International,",
  "assessmentLength": "Approximate Completion Time in minutes = 30",
  "productFactSheet": [
    "https://service.shl.com/docs/Fact_Sheet-Written_English_US.pdf"
  ]
}